Workbook
Name KategorienListe: Einstellungen!$A$4:$A$40
Name KontenListe: Einstellungen!$F$4:$F$15
Name RhythmusListe: Einstellungen!$H$4:$H$7

Sheet Anleitung
A1: Finanzplaner – Anleitung
A2: Erstellt für Sarah · Alle Beträge in Euro (€)
A4: Deine Konten und Karten
A5: Stand 18.08.2026. Die Salden holt sich die Tabelle aus dem Blatt Vermögen – trag dort einmal im Monat die Kontostände ein, dann bleibt diese Übersicht aktuell.
A6: Konto | B6: Inhaber | C6: IBAN / Kartennummer | D6: Saldo (€) | E6: Import: --konto "…"
A7: S-POOL light+ | B7: Sarah Maxara | C7: DE25 3055 0000 1005 4402 90 | D7: =IFERROR(LOOKUP(9.99999999999999E+307,Vermögen!$B$4:$B$27),0) | E7: Girokonto
A8: Giro Express Plus | B8: Marvin Liskatin, Sarah Maxara | C8: DE77 3055 0000 1005 4403 24 | D8: =IFERROR(LOOKUP(9.99999999999999E+307,Vermögen!$F$4:$F$27),0) | E8: Gemeinschaftskonto
A9: Tagesgeldkonto+ | B9: Sarah Maxara | C9: DE59 3055 0000 1005 4403 57 | D9: =IFERROR(LOOKUP(9.99999999999999E+307,Vermögen!$C$4:$C$27),0) | E9: Tagesgeld / Sparkonto
A10: Gold Privat (Kreditkarte) | B10: Sarah Maxara | C10: 5232 **** **** 6059 | D10: =-IFERROR(LOOKUP(9.99999999999999E+307,Vermögen!$H$4:$H$27),0) | E10: Kreditkarte
A11: Nettovermögen (Summe) | D11: =SUM(D7:D10)
A12: Hinweis: Das Giro Express Plus führst du gemeinsam mit Marvin – hier zählt es voll als dein Guthaben. Willst du nur die Hälfte rechnen, trag im Blatt Vermögen entsprechend den halben Betrag ein.
A14: In drei Schritten aktuell halten
A15: 1. Exportieren | B15: Für jedes der vier Konten im Online-Banking die Umsätze als CSV herunterladen und in denselben Ordner legen wie diese Datei.
A16: 2. Importieren | B16: Diese Datei schließen. Dann im Terminal je CSV einmal aufrufen, z. B.: python import_umsaetze.py umsaetze.CSV --konto "Girokonto" – den passenden Namen findest du oben in der letzten Spalte.
A17: 3. Öffnen | B17: Datei wieder öffnen. Monatsübersicht, Kategorien, Dashboard und alle Diagramme haben sich automatisch neu berechnet – nichts abtippen.
A18: Gut zu wissen | B18: Ein Import kann nichts doppelt eintragen: bereits vorhandene Buchungen werden an der Import-ID in Spalte J erkannt und übersprungen. Mit --dry-run siehst du vorab, was passieren würde, ohne dass etwas geschrieben wird.
A20: Die Blätter der Datei
A21: Dashboard | B21: Startseite: Kennzahlen des laufenden Monats, deine Kontostände und die fünf Diagramme. Über jedem Diagramm steht, was es zeigt.
A22: Buchungen | B22: Das Herzstück – jede Einnahme und Ausgabe als eigene Zeile. Füllt normalerweise das Import-Skript; du kannst aber jederzeit von Hand korrigieren, vor allem die Kategorie in Spalte D.
A23: Einstellungen | B23: Deine Kategorien, das Monatsbudget je Kategorie und die Liste der Konten. Neue Kategorie? Einfach in eine freie Zeile schreiben.
A24: Fixkosten | B24: Wiederkehrende Kosten mit Rhythmus. Jährliche und vierteljährliche Beträge werden auf den Monat umgerechnet.
A25: Monatsübersicht | B25: Pro Monat: Einnahmen, Ausgaben, Saldo, Sparquote und der kumulierte Verlauf. Rechnet sich vollständig selbst.
A26: Kategorien | B26: Kreuztabelle Kategorie × Monat für ein Jahr, mit Vergleich gegen dein Budget. Das Jahr stellst du oben in B3 ein.
A27: Sparziele | B27: Ziele mit Zielbetrag und Monatsrate, dazu Fortschritt und voraussichtliches Zieldatum.
A28: Vermögen | B28: Einmal im Monat die Kontostände eintragen. Daraus entstehen Nettovermögen, Veränderung und die Konten-Übersicht ganz oben.
A29: Prognose | B29: Hochrechnung deines Vermögens für 12 Monate auf Basis deiner tatsächlichen Sparrate.
A31: Farblegende
A32: Blaue Schrift | B32: Fest eingetragener Wert – hier darfst du tippen.
A33: Gelb hinterlegt | B33: Zellen, die du ausfüllen bzw. anpassen solltest.
A34: Schwarze Schrift | B34: Berechnete Formel – bitte nicht überschreiben.
A35: Grüne Schrift | B35: Verweis auf ein anderes Blatt – ebenfalls Formel.
A37: Wichtige Hinweise
A38: Beispielzeilen | B38: In Buchungen, Fixkosten und Sparziele steht je eine graue BEISPIEL-Zeile als Formatvorlage. Einfach überschreiben oder leeren.
A39: Zeitraum | B39: Monatsübersicht, Vermögen und Prognose laufen von Januar 2026 bis Dezember 2027. Das Blatt Buchungen fasst 1.000 Zeilen.
A40: Sparen ist keine Ausgabe | B40: Überweisungen auf dein Tagesgeld sind keine Ausgabe – sonst zählt die Sparquote doppelt. Solche Umbuchungen am besten aus den Buchungen löschen und nur im Blatt Vermögen abbilden.
A41: Eigene Diagramme | B41: Das Import-Skript baut die Diagramme auf dem Dashboard bei jedem Lauf neu. Eigene Grafiken deshalb lieber auf einem separaten Blatt anlegen, sonst sind sie nach dem nächsten Import weg.

Sheet Dashboard
A1: Dashboard
A2: Kennzahlen des laufenden Monats · alles automatisch berechnet
D3: Einnahmen und Ausgaben je Monat | P3: Kontostände je Konto
A4: Laufender Monat | D4: Zwei Balken pro Monat: was reingekommen ist und was rausgegangen ist. Ist der rechte Balken höher, war der Monat im Minus. | P4: Der zuletzt im Blatt Vermögen eingetragene Stand deiner drei Konten und der Kreditkarte. Die Kreditkarte zeigt nach unten, weil sie Schulden sind.
A5: Aktueller Monat | B5: =TODAY()
A6: Einnahmen | B6: =SUMIFS(Buchungen!$F$4:$F$1003,Buchungen!$B$4:$B$1003,YEAR(TODAY()),Buchungen!$C$4:$C$1003,MONTH(TODAY()),Buchungen!$G$4:$G$1003,"Einnahme")
A7: Ausgaben | B7: =SUMIFS(Buchungen!$F$4:$F$1003,Buchungen!$B$4:$B$1003,YEAR(TODAY()),Buchungen!$C$4:$C$1003,MONTH(TODAY()),Buchungen!$G$4:$G$1003,"Ausgabe")
A8: Saldo | B8: =$B$6-$B$7
A9: Sparquote | B9: =IF($B$6<=0,0,$B$8/$B$6)
A11: Struktur & Durchschnitte
A12: Fixkosten pro Monat | B12: =Fixkosten!$F$35
A13: Budget gesamt pro Monat | B13: =Einstellungen!$C$42
A14: Ø Ausgaben (Monate mit Daten) | B14: =IFERROR(AVERAGEIF(Monatsübersicht!$E$4:$E$27,"<>0"),0)
A15: Ø Sparrate (Monate mit Daten) | B15: =IFERROR(AVERAGEIF(Monatsübersicht!$F$4:$F$27,"<>0"),0)
A16: Nettovermögen aktuell | B16: =Prognose!$B$5
A17: Prognose Vermögen in 12 Monaten | B17: =Prognose!$C$29
A19: Top-Ausgabenkategorie (Jahr laut Blatt Kategorien)
A20: Kategorie | B20: =IFERROR(INDEX(Kategorien!$A$6:$A$42,MATCH(MAX(Kategorien!$S$6:$S$42),Kategorien!$S$6:$S$42,0)),"–")
A21: Betrag | B21: =MAX(Kategorien!$S$6:$S$42)
D23: Kumulierter Saldo seit Januar | P23: Nettovermögen im Zeitverlauf
A24: Alle Zahlen aktualisieren sich, sobald du im Blatt Buchungen neue Zeilen erfasst. | D24: Alle Monatssalden aufaddiert. Steigt die Linie, hast du unterm Strich gespart; fällt sie, hast du mehr ausgegeben als eingenommen. | P24: Hier entsteht eine Kurve, sobald im Blatt Vermögen mindestens zwei Monate mit Kontoständen stehen. Aktuell ist erst einer erfasst.
A26: Kontostände (letzter Eintrag im Blatt Vermögen)
A27: Konto | B27: Saldo (€)
A28: S-POOL light+ | B28: =IFERROR(LOOKUP(9.99999999999999E+307,Vermögen!$B$4:$B$27),0)
A29: Giro Express Plus | B29: =IFERROR(LOOKUP(9.99999999999999E+307,Vermögen!$F$4:$F$27),0)
A30: Tagesgeldkonto+ | B30: =IFERROR(LOOKUP(9.99999999999999E+307,Vermögen!$C$4:$C$27),0)
A31: Gold Privat (Kreditkarte) | B31: =-IFERROR(LOOKUP(9.99999999999999E+307,Vermögen!$H$4:$H$27),0)
A32: Summe | B32: =SUM(B28:B31)
D43: Ausgaben je Kategorie | P43: Prognose der nächsten 12 Monate
D44: Womit ist im Jahr aus dem Blatt Kategorien das Geld weggegangen? Der längste Balken ist dein größter Posten. | P44: Fortschreibung deines Nettovermögens mit deiner bisherigen Sparrate. Die Annahmen dazu stehen im Blatt Prognose.

Sheet Buchungen
A1: Buchungen
A2: Jede Einnahme und Ausgabe als eigene Zeile · Beträge immer positiv eintragen
A3: Datum | B3: Jahr | C3: Monat | D3: Kategorie | E3: Beschreibung | F3: Betrag (€) | G3: Typ | H3: Konto | I3: Wirkung (€) | J3: Import-ID
A4: 46025 | B4: =IF($A4="","",YEAR($A4)) | C4: =IF($A4="","",MONTH($A4)) | D4: Lebensmittel | E4: BEISPIEL – Zeile überschreiben oder Inhalt löschen | F4: 42.5 | G4: =IF($D4="","",IFERROR(INDEX(Einstellungen!$B$4:$B$40,MATCH($D4,Einstellungen!$A$4:$A$40,0)),"?")) | H4: Girokonto | I4: =IF($F4="","",IF($G4="Einnahme",$F4,-$F4))
A5: 46204 | B5: =IF($A5="","",YEAR($A5)) | C5: =IF($A5="","",MONTH($A5)) | D5: Sonstiges | E5: Entgeltabrechnung siehe Anlage Abrechnung 30.06.2026 Information zur Abrechnung Entgelte vom 26.06.2026 bis 30.06.2026 0,48- Grundpreis (Kontoführung) 0,48- Abrechnung 30.06.2026 0,48- Es handelt sich | F5: 0.48 | G5: =IF($D5="","",IFERROR(INDEX(Einstellungen!$B$4:$B$40,MATCH($D5,Einstellungen!$A$4:$A$40,0)),"?")) | H5: Girokonto | I5: =IF($F5="","",IF($G5="Einnahme",$F5,-$F5)) | J5: 59b57f954c8fd10b
A6: 46216 | B6: =IF($A6="","",YEAR($A6)) | C6: =IF($A6="","",MONTH($A6)) | D6: Restaurant & Lieferdienst | E6: Lieferando.de lieferse/Oosterdoksstraat 80/Amsterdam/NL/1 – 2026-07-11T13:52 Debitk.10 2030-12 Zahl.System DebitMastercard | F6: 39.22 | G6: =IF($D6="","",IFERROR(INDEX(Einstellungen!$B$4:$B$40,MATCH($D6,Einstellungen!$A$4:$A$40,0)),"?")) | H6: Girokonto | I6: =IF($F6="","",IF($G6="Einnahme",$F6,-$F6)) | J6: c758ba4c1bd191bd
A7: 46217 | B7: =IF($A7="","",YEAR($A7)) | C7: =IF($A7="","",MONTH($A7)) | D7: Restaurant & Lieferdienst | E7: Lieferando.de/Oosterdoksstraat 80/Amsterdam/NL – 2026-07-13T21:25 Debitk.10 2030-12 | F7: 52.23 | G7: =IF($D7="","",IFERROR(INDEX(Einstellungen!$B$4:$B$40,MATCH($D7,Einstellungen!$A$4:$A$40,0)),"?")) | H7: Girokonto | I7: =IF($F7="","",IF($G7="Einnahme",$F7,-$F7)) | J7: 4b7ba1a15f3261de
A8: 46230 | B8: =IF($A8="","",YEAR($A8)) | C8: =IF($A8="","",MONTH($A8)) | D8: Sonstige Einnahmen | E8: Sarah-Luise Maxara | F8: 100 | G8: =IF($D8="","",IFERROR(INDEX(Einstellungen!$B$4:$B$40,MATCH($D8,Einstellungen!$A$4:$A$40,0)),"?")) | H8: Girokonto | I8: =IF($F8="","",IF($G8="Einnahme",$F8,-$F8)) | J8: 5272ed3d5f242ea9
A9: 46231 | B9: =IF($A9="","",YEAR($A9)) | C9: =IF($A9="","",MONTH($A9)) | D9: Sonstige Einnahmen | E9: Sarah-Luise Maxara – Konto 146387097 Ausgleich des Kontosaldos wegen Kontoauflösung | F9: 417.41 | G9: =IF($D9="","",IFERROR(INDEX(Einstellungen!$B$4:$B$40,MATCH($D9,Einstellungen!$A$4:$A$40,0)),"?")) | H9: Girokonto | I9: =IF($F9="","",IF($G9="Einnahme",$F9,-$F9)) | J9: 8133c60b7c9b8cc5
A10: 46233 | B10: =IF($A10="","",YEAR($A10)) | C10: =IF($A10="","",MONTH($A10)) | D10: Strom & Internet | E10: MARVIN LISKATIN UND SARAH M AXARA – DATUM 30.07.2026, 11.23 UHR | F10: 300 | G10: =IF($D10="","",IFERROR(INDEX(Einstellungen!$B$4:$B$40,MATCH($D10,Einstellungen!$A$4:$A$40,0)),"?")) | H10: Girokonto | I10: =IF($F10="","",IF($G10="Einnahme",$F10,-$F10)) | J10: e4d39054a67ebdca
A11: 46233 | B11: =IF($A11="","",YEAR($A11)) | C11: =IF($A11="","",MONTH($A11)) | D11: Restaurant & Lieferdienst | E11: 01044 MCDONALDS//DUESSELDORF/DE – 2026-07-29T23:06 Debitk.10 2030-12 | F11: 30.27 | G11: =IF($D11="","",IFERROR(INDEX(Einstellungen!$B$4:$B$40,MATCH($D11,Einstellungen!$A$4:$A$40,0)),"?")) | H11: Girokonto | I11: =IF($F11="","",IF($G11="Einnahme",$F11,-$F11)) | J11: 9477000bb0038ab8
A12: 46234 | B12: =IF($A12="","",YEAR($A12)) | C12: =IF($A12="","",MONTH($A12)) | D12: Sonstige Einnahmen | E12: Barbara Maxara – Mtl Auto und Semesterbeitrag | F12: 300 | G12: =IF($D12="","",IFERROR(INDEX(Einstellungen!$B$4:$B$40,MATCH($D12,Einstellungen!$A$4:$A$40,0)),"?")) | H12: Girokonto | I12: =IF($F12="","",IF($G12="Einnahme",$F12,-$F12)) | J12: 35b94d6e6ec7f9af
A13: 46234 | B13: =IF($A13="","",YEAR($A13)) | C13: =IF($A13="","",MONTH($A13)) | D13: Restaurant & Lieferdienst | E13: Lieferando.de/Oosterdoksstraat 80/Amsterdam/NL – 2026-07-30T20:55 Debitk.10 2030-12 | F13: 25.15 | G13: =IF($D13="","",IFERROR(INDEX(Einstellungen!$B$4:$B$40,MATCH($D13,Einstellungen!$A$4:$A$40,0)),"?")) | H13: Girokonto | I13: =IF($F13="","",IF($G13="Einnahme",$F13,-$F13)) | J13: b384d6a4f23a5ef9
A14: 46234 | B14: =IF($A14="","",YEAR($A14)) | C14: =IF($A14="","",MONTH($A14)) | D14: Lebensmittel | E14: NETTO MARKEN-DISCOU/DORFSTR. 26/MEERBUSCH/DE – 2026-07-30T16:58 Debitk.0 2030-12 | F14: 19.87 | G14: =IF($D14="","",IFERROR(INDEX(Einstellungen!$B$4:$B$40,MATCH($D14,Einstellungen!$A$4:$A$40,0)),"?")) | H14: Girokonto | I14: =IF($F14="","",IF($G14="Einnahme",$F14,-$F14)) | J14: 66d68658b603bbe8
A15: 46234 | B15: =IF($A15="","",YEAR($A15)) | C15: =IF($A15="","",MONTH($A15)) | D15: Sonstige Einnahmen | E15: Marvin Liskatin – Döner | F15: 30 | G15: =IF($D15="","",IFERROR(INDEX(Einstellungen!$B$4:$B$40,MATCH($D15,Einstellungen!$A$4:$A$40,0)),"?")) | H15: Girokonto | I15: =IF($F15="","",IF($G15="Einnahme",$F15,-$F15)) | J15: 635443a001368929
A16: 46237 | B16: =IF($A16="","",YEAR($A16)) | C16: =IF($A16="","",MONTH($A16)) | D16: Gesundheit & Drogerie | E16: MAURITIUS-APOTHEKE//MEERBUSCH/DE – 2026-07-31T10:35 Debitk.0 2030-12 | F16: 5 | G16: =IF($D16="","",IFERROR(INDEX(Einstellungen!$B$4:$B$40,MATCH($D16,Einstellungen!$A$4:$A$40,0)),"?")) | H16: Girokonto | I16: =IF($F16="","",IF($G16="Einnahme",$F16,-$F16)) | J16: 12fd6bb9bfa2f49a
... A77: 46247 | B77: =IF($A77="","",YEAR($A77)) | C77: =IF($A77="","",MONTH($A77)) | D77: Sonstige Einnahmen | E77: Marvin Liskatin | F77: 100 | G77: =IF($D77="","",IFERROR(INDEX(Einstellungen!$B$4:$B$40,MATCH($D77,Einstellungen!$A$4:$A$40,0)),"?")) | H77: Gemeinschaftskonto | I77: =IF($F77="","",IF($G77="Einnahme",$F77,-$F77)) | J77: 858296a1a85b8bf1
B78: =IF($A78="","",YEAR($A78)) | C78: =IF($A78="","",MONTH($A78)) | G78: =IF($D78="","",IFERROR(INDEX(Einstellungen!$B$4:$B$40,MATCH($D78,Einstellungen!$A$4:$A$40,0)),"?")) | I78: =IF($F78="","",IF($G78="Einnahme",$F78,-$F78))
B79: =IF($A79="","",YEAR($A79)) | C79: =IF($A79="","",MONTH($A79)) | G79: =IF($D79="","",IFERROR(INDEX(Einstellungen!$B$4:$B$40,MATCH($D79,Einstellungen!$A$4:$A$40,0)),"?")) | I79: =IF($F79="","",IF($G79="Einnahme",$F79,-$F79))
B80: =IF($A80="","",YEAR($A80)) | C80: =IF($A80="","",MONTH($A80)) | G80: =IF($D80="","",IFERROR(INDEX(Einstellungen!$B$4:$B$40,MATCH($D80,Einstellungen!$A$4:$A$40,0)),"?")) | I80: =IF($F80="","",IF($G80="Einnahme",$F80,-$F80))
B81: =IF($A81="","",YEAR($A81)) | C81: =IF($A81="","",MONTH($A81)) | G81: =IF($D81="","",IFERROR(INDEX(Einstellungen!$B$4:$B$40,MATCH($D81,Einstellungen!$A$4:$A$40,0)),"?")) | I81: =IF($F81="","",IF($G81="Einnahme",$F81,-$F81))
B82: =IF($A82="","",YEAR($A82)) | C82: =IF($A82="","",MONTH($A82)) | G82: =IF($D82="","",IFERROR(INDEX(Einstellungen!$B$4:$B$40,MATCH($D82,Einstellungen!$A$4:$A$40,0)),"?")) | I82: =IF($F82="","",IF($G82="Einnahme",$F82,-$F82))
B83: =IF($A83="","",YEAR($A83)) | C83: =IF($A83="","",MONTH($A83)) | G83: =IF($D83="","",IFERROR(INDEX(Einstellungen!$B$4:$B$40,MATCH($D83,Einstellungen!$A$4:$A$40,0)),"?")) | I83: =IF($F83="","",IF($G83="Einnahme",$F83,-$F83))
B84: =IF($A84="","",YEAR($A84)) | C84: =IF($A84="","",MONTH($A84)) | G84: =IF($D84="","",IFERROR(INDEX(Einstellungen!$B$4:$B$40,MATCH($D84,Einstellungen!$A$4:$A$40,0)),"?")) | I84: =IF($F84="","",IF($G84="Einnahme",$F84,-$F84))
B85: =IF($A85="","",YEAR($A85)) | C85: =IF($A85="","",MONTH($A85)) | G85: =IF($D85="","",IFERROR(INDEX(Einstellungen!$B$4:$B$40,MATCH($D85,Einstellungen!$A$4:$A$40,0)),"?")) | I85: =IF($F85="","",IF($G85="Einnahme",$F85,-$F85))
B86: =IF($A86="","",YEAR($A86)) | C86: =IF($A86="","",MONTH($A86)) | G86: =IF($D86="","",IFERROR(INDEX(Einstellungen!$B$4:$B$40,MATCH($D86,Einstellungen!$A$4:$A$40,0)),"?")) | I86: =IF($F86="","",IF($G86="Einnahme",$F86,-$F86))
B87: =IF($A87="","",YEAR($A87)) | C87: =IF($A87="","",MONTH($A87)) | G87: =IF($D87="","",IFERROR(INDEX(Einstellungen!$B$4:$B$40,MATCH($D87,Einstellungen!$A$4:$A$40,0)),"?")) | I87: =IF($F87="","",IF($G87="Einnahme",$F87,-$F87))
B88: =IF($A88="","",YEAR($A88)) | C88: =IF($A88="","",MONTH($A88)) | G88: =IF($D88="","",IFERROR(INDEX(Einstellungen!$B$4:$B$40,MATCH($D88,Einstellungen!$A$4:$A$40,0)),"?")) | I88: =IF($F88="","",IF($G88="Einnahme",$F88,-$F88))
B89: =IF($A89="","",YEAR($A89)) | C89: =IF($A89="","",MONTH($A89)) | G89: =IF($D89="","",IFERROR(INDEX(Einstellungen!$B$4:$B$40,MATCH($D89,Einstellungen!$A$4:$A$40,0)),"?")) | I89: =IF($F89="","",IF($G89="Einnahme",$F89,-$F89))
... B1003: =IF($A1003="","",YEAR($A1003)) | C1003: =IF($A1003="","",MONTH($A1003)) | G1003: =IF($D1003="","",IFERROR(INDEX(Einstellungen!$B$4:$B$40,MATCH($D1003,Einstellungen!$A$4:$A$40,0)),"?")) | I1003: =IF($F1003="","",IF($G1003="Einnahme",$F1003,-$F1003))

Sheet Fixkosten
A1: Fixkosten
A2: Wiederkehrende Kosten – automatisch auf Monats- und Jahreswerte umgerechnet
A3: Bezeichnung | B3: Kategorie | C3: Betrag (€) | D3: Rhythmus | E3: Zahlungen/Jahr | F3: Monatlich (€) | G3: Jährlich (€) | H3: Nächste Fälligkeit | I3: Konto | J3: Notiz
A4: BEISPIEL – Miete WG-Zimmer | B4: Miete & Nebenkosten | C4: 520 | D4: monatlich | E4: =IF($D4="","",IF($D4="monatlich",12,IF($D4="vierteljährlich",4,IF($D4="halbjährlich",2,IF($D4="jährlich",1,""))))) | F4: =IF($E4="","",$C4*$E4/12) | G4: =IF($E4="","",$C4*$E4) | H4: 46266 | I4: Girokonto | J4: Beispielzeile – bitte überschreiben
E5: =IF($D5="","",IF($D5="monatlich",12,IF($D5="vierteljährlich",4,IF($D5="halbjährlich",2,IF($D5="jährlich",1,""))))) | F5: =IF($E5="","",$C5*$E5/12) | G5: =IF($E5="","",$C5*$E5)
E6: =IF($D6="","",IF($D6="monatlich",12,IF($D6="vierteljährlich",4,IF($D6="halbjährlich",2,IF($D6="jährlich",1,""))))) | F6: =IF($E6="","",$C6*$E6/12) | G6: =IF($E6="","",$C6*$E6)
E7: =IF($D7="","",IF($D7="monatlich",12,IF($D7="vierteljährlich",4,IF($D7="halbjährlich",2,IF($D7="jährlich",1,""))))) | F7: =IF($E7="","",$C7*$E7/12) | G7: =IF($E7="","",$C7*$E7)
E8: =IF($D8="","",IF($D8="monatlich",12,IF($D8="vierteljährlich",4,IF($D8="halbjährlich",2,IF($D8="jährlich",1,""))))) | F8: =IF($E8="","",$C8*$E8/12) | G8: =IF($E8="","",$C8*$E8)
E9: =IF($D9="","",IF($D9="monatlich",12,IF($D9="vierteljährlich",4,IF($D9="halbjährlich",2,IF($D9="jährlich",1,""))))) | F9: =IF($E9="","",$C9*$E9/12) | G9: =IF($E9="","",$C9*$E9)
E10: =IF($D10="","",IF($D10="monatlich",12,IF($D10="vierteljährlich",4,IF($D10="halbjährlich",2,IF($D10="jährlich",1,""))))) | F10: =IF($E10="","",$C10*$E10/12) | G10: =IF($E10="","",$C10*$E10)
E11: =IF($D11="","",IF($D11="monatlich",12,IF($D11="vierteljährlich",4,IF($D11="halbjährlich",2,IF($D11="jährlich",1,""))))) | F11: =IF($E11="","",$C11*$E11/12) | G11: =IF($E11="","",$C11*$E11)
E12: =IF($D12="","",IF($D12="monatlich",12,IF($D12="vierteljährlich",4,IF($D12="halbjährlich",2,IF($D12="jährlich",1,""))))) | F12: =IF($E12="","",$C12*$E12/12) | G12: =IF($E12="","",$C12*$E12)
E13: =IF($D13="","",IF($D13="monatlich",12,IF($D13="vierteljährlich",4,IF($D13="halbjährlich",2,IF($D13="jährlich",1,""))))) | F13: =IF($E13="","",$C13*$E13/12) | G13: =IF($E13="","",$C13*$E13)
E14: =IF($D14="","",IF($D14="monatlich",12,IF($D14="vierteljährlich",4,IF($D14="halbjährlich",2,IF($D14="jährlich",1,""))))) | F14: =IF($E14="","",$C14*$E14/12) | G14: =IF($E14="","",$C14*$E14)
E15: =IF($D15="","",IF($D15="monatlich",12,IF($D15="vierteljährlich",4,IF($D15="halbjährlich",2,IF($D15="jährlich",1,""))))) | F15: =IF($E15="","",$C15*$E15/12) | G15: =IF($E15="","",$C15*$E15)
E16: =IF($D16="","",IF($D16="monatlich",12,IF($D16="vierteljährlich",4,IF($D16="halbjährlich",2,IF($D16="jährlich",1,""))))) | F16: =IF($E16="","",$C16*$E16/12) | G16: =IF($E16="","",$C16*$E16)
... E33: =IF($D33="","",IF($D33="monatlich",12,IF($D33="vierteljährlich",4,IF($D33="halbjährlich",2,IF($D33="jährlich",1,""))))) | F33: =IF($E33="","",$C33*$E33/12) | G33: =IF($E33="","",$C33*$E33)
A35: Summe | F35: =SUM(F4:F33) | G35: =SUM(G4:G33)
A37: Hinweis: Fixkosten sind hier nur GEPLANT. Die tatsächliche Zahlung trägst du zusätzlich in Buchungen ein.

Sheet Monatsübersicht
A1: Monatsübersicht
A2: Vollautomatisch aus dem Blatt Buchungen – hier nichts eintragen
A3: Monat | B3: Jahr | C3: Nr. | D3: Einnahmen (€) | E3: Ausgaben (€) | F3: Saldo (€) | G3: Sparquote | H3: Kumuliert (€) | I3: Ø Ausgaben 3M (€) | J3: Ø Saldo 3M (€) | K3: Budget Soll (€) | L3: Abweichung (€) | M3: Lfd. Nr.
A4: 46023 | B4: =YEAR($A4) | C4: =MONTH($A4) | D4: =SUMIFS(Buchungen!$F$4:$F$1003,Buchungen!$B$4:$B$1003,$B4,Buchungen!$C$4:$C$1003,$C4,Buchungen!$G$4:$G$1003,"Einnahme") | E4: =SUMIFS(Buchungen!$F$4:$F$1003,Buchungen!$B$4:$B$1003,$B4,Buchungen!$C$4:$C$1003,$C4,Buchungen!$G$4:$G$1003,"Ausgabe") | F4: =$D4-$E4 | G4: =IF($D4<=0,0,$F4/$D4) | H4: =$F4 | K4: =Einstellungen!$C$42 | L4: =$K4-$E4 | M4: 1
A5: 46054 | B5: =YEAR($A5) | C5: =MONTH($A5) | D5: =SUMIFS(Buchungen!$F$4:$F$1003,Buchungen!$B$4:$B$1003,$B5,Buchungen!$C$4:$C$1003,$C5,Buchungen!$G$4:$G$1003,"Einnahme") | E5: =SUMIFS(Buchungen!$F$4:$F$1003,Buchungen!$B$4:$B$1003,$B5,Buchungen!$C$4:$C$1003,$C5,Buchungen!$G$4:$G$1003,"Ausgabe") | F5: =$D5-$E5 | G5: =IF($D5<=0,0,$F5/$D5) | H5: =$H4+$F5 | K5: =Einstellungen!$C$42 | L5: =$K5-$E5 | M5: 2
A6: 46082 | B6: =YEAR($A6) | C6: =MONTH($A6) | D6: =SUMIFS(Buchungen!$F$4:$F$1003,Buchungen!$B$4:$B$1003,$B6,Buchungen!$C$4:$C$1003,$C6,Buchungen!$G$4:$G$1003,"Einnahme") | E6: =SUMIFS(Buchungen!$F$4:$F$1003,Buchungen!$B$4:$B$1003,$B6,Buchungen!$C$4:$C$1003,$C6,Buchungen!$G$4:$G$1003,"Ausgabe") | F6: =$D6-$E6 | G6: =IF($D6<=0,0,$F6/$D6) | H6: =$H5+$F6 | I6: =AVERAGE($E4:$E6) | J6: =AVERAGE($F4:$F6) | K6: =Einstellungen!$C$42 | L6: =$K6-$E6 | M6: 3
A7: 46113 | B7: =YEAR($A7) | C7: =MONTH($A7) | D7: =SUMIFS(Buchungen!$F$4:$F$1003,Buchungen!$B$4:$B$1003,$B7,Buchungen!$C$4:$C$1003,$C7,Buchungen!$G$4:$G$1003,"Einnahme") | E7: =SUMIFS(Buchungen!$F$4:$F$1003,Buchungen!$B$4:$B$1003,$B7,Buchungen!$C$4:$C$1003,$C7,Buchungen!$G$4:$G$1003,"Ausgabe") | F7: =$D7-$E7 | G7: =IF($D7<=0,0,$F7/$D7) | H7: =$H6+$F7 | I7: =AVERAGE($E5:$E7) | J7: =AVERAGE($F5:$F7) | K7: =Einstellungen!$C$42 | L7: =$K7-$E7 | M7: 4
A8: 46143 | B8: =YEAR($A8) | C8: =MONTH($A8) | D8: =SUMIFS(Buchungen!$F$4:$F$1003,Buchungen!$B$4:$B$1003,$B8,Buchungen!$C$4:$C$1003,$C8,Buchungen!$G$4:$G$1003,"Einnahme") | E8: =SUMIFS(Buchungen!$F$4:$F$1003,Buchungen!$B$4:$B$1003,$B8,Buchungen!$C$4:$C$1003,$C8,Buchungen!$G$4:$G$1003,"Ausgabe") | F8: =$D8-$E8 | G8: =IF($D8<=0,0,$F8/$D8) | H8: =$H7+$F8 | I8: =AVERAGE($E6:$E8) | J8: =AVERAGE($F6:$F8) | K8: =Einstellungen!$C$42 | L8: =$K8-$E8 | M8: 5
A9: 46174 | B9: =YEAR($A9) | C9: =MONTH($A9) | D9: =SUMIFS(Buchungen!$F$4:$F$1003,Buchungen!$B$4:$B$1003,$B9,Buchungen!$C$4:$C$1003,$C9,Buchungen!$G$4:$G$1003,"Einnahme") | E9: =SUMIFS(Buchungen!$F$4:$F$1003,Buchungen!$B$4:$B$1003,$B9,Buchungen!$C$4:$C$1003,$C9,Buchungen!$G$4:$G$1003,"Ausgabe") | F9: =$D9-$E9 | G9: =IF($D9<=0,0,$F9/$D9) | H9: =$H8+$F9 | I9: =AVERAGE($E7:$E9) | J9: =AVERAGE($F7:$F9) | K9: =Einstellungen!$C$42 | L9: =$K9-$E9 | M9: 6
A10: 46204 | B10: =YEAR($A10) | C10: =MONTH($A10) | D10: =SUMIFS(Buchungen!$F$4:$F$1003,Buchungen!$B$4:$B$1003,$B10,Buchungen!$C$4:$C$1003,$C10,Buchungen!$G$4:$G$1003,"Einnahme") | E10: =SUMIFS(Buchungen!$F$4:$F$1003,Buchungen!$B$4:$B$1003,$B10,Buchungen!$C$4:$C$1003,$C10,Buchungen!$G$4:$G$1003,"Ausgabe") | F10: =$D10-$E10 | G10: =IF($D10<=0,0,$F10/$D10) | H10: =$H9+$F10 | I10: =AVERAGE($E8:$E10) | J10: =AVERAGE($F8:$F10) | K10: =Einstellungen!$C$42 | L10: =$K10-$E10 | M10: 7
A11: 46235 | B11: =YEAR($A11) | C11: =MONTH($A11) | D11: =SUMIFS(Buchungen!$F$4:$F$1003,Buchungen!$B$4:$B$1003,$B11,Buchungen!$C$4:$C$1003,$C11,Buchungen!$G$4:$G$1003,"Einnahme") | E11: =SUMIFS(Buchungen!$F$4:$F$1003,Buchungen!$B$4:$B$1003,$B11,Buchungen!$C$4:$C$1003,$C11,Buchungen!$G$4:$G$1003,"Ausgabe") | F11: =$D11-$E11 | G11: =IF($D11<=0,0,$F11/$D11) | H11: =$H10+$F11 | I11: =AVERAGE($E9:$E11) | J11: =AVERAGE($F9:$F11) | K11: =Einstellungen!$C$42 | L11: =$K11-$E11 | M11: 8
A12: 46266 | B12: =YEAR($A12) | C12: =MONTH($A12) | D12: =SUMIFS(Buchungen!$F$4:$F$1003,Buchungen!$B$4:$B$1003,$B12,Buchungen!$C$4:$C$1003,$C12,Buchungen!$G$4:$G$1003,"Einnahme") | E12: =SUMIFS(Buchungen!$F$4:$F$1003,Buchungen!$B$4:$B$1003,$B12,Buchungen!$C$4:$C$1003,$C12,Buchungen!$G$4:$G$1003,"Ausgabe") | F12: =$D12-$E12 | G12: =IF($D12<=0,0,$F12/$D12) | H12: =$H11+$F12 | I12: =AVERAGE($E10:$E12) | J12: =AVERAGE($F10:$F12) | K12: =Einstellungen!$C$42 | L12: =$K12-$E12 | M12: 9
A13: 46296 | B13: =YEAR($A13) | C13: =MONTH($A13) | D13: =SUMIFS(Buchungen!$F$4:$F$1003,Buchungen!$B$4:$B$1003,$B13,Buchungen!$C$4:$C$1003,$C13,Buchungen!$G$4:$G$1003,"Einnahme") | E13: =SUMIFS(Buchungen!$F$4:$F$1003,Buchungen!$B$4:$B$1003,$B13,Buchungen!$C$4:$C$1003,$C13,Buchungen!$G$4:$G$1003,"Ausgabe") | F13: =$D13-$E13 | G13: =IF($D13<=0,0,$F13/$D13) | H13: =$H12+$F13 | I13: =AVERAGE($E11:$E13) | J13: =AVERAGE($F11:$F13) | K13: =Einstellungen!$C$42 | L13: =$K13-$E13 | M13: 10
A14: 46327 | B14: =YEAR($A14) | C14: =MONTH($A14) | D14: =SUMIFS(Buchungen!$F$4:$F$1003,Buchungen!$B$4:$B$1003,$B14,Buchungen!$C$4:$C$1003,$C14,Buchungen!$G$4:$G$1003,"Einnahme") | E14: =SUMIFS(Buchungen!$F$4:$F$1003,Buchungen!$B$4:$B$1003,$B14,Buchungen!$C$4:$C$1003,$C14,Buchungen!$G$4:$G$1003,"Ausgabe") | F14: =$D14-$E14 | G14: =IF($D14<=0,0,$F14/$D14) | H14: =$H13+$F14 | I14: =AVERAGE($E12:$E14) | J14: =AVERAGE($F12:$F14) | K14: =Einstellungen!$C$42 | L14: =$K14-$E14 | M14: 11
A15: 46357 | B15: =YEAR($A15) | C15: =MONTH($A15) | D15: =SUMIFS(Buchungen!$F$4:$F$1003,Buchungen!$B$4:$B$1003,$B15,Buchungen!$C$4:$C$1003,$C15,Buchungen!$G$4:$G$1003,"Einnahme") | E15: =SUMIFS(Buchungen!$F$4:$F$1003,Buchungen!$B$4:$B$1003,$B15,Buchungen!$C$4:$C$1003,$C15,Buchungen!$G$4:$G$1003,"Ausgabe") | F15: =$D15-$E15 | G15: =IF($D15<=0,0,$F15/$D15) | H15: =$H14+$F15 | I15: =AVERAGE($E13:$E15) | J15: =AVERAGE($F13:$F15) | K15: =Einstellungen!$C$42 | L15: =$K15-$E15 | M15: 12
A16: 46388 | B16: =YEAR($A16) | C16: =MONTH($A16) | D16: =SUMIFS(Buchungen!$F$4:$F$1003,Buchungen!$B$4:$B$1003,$B16,Buchungen!$C$4:$C$1003,$C16,Buchungen!$G$4:$G$1003,"Einnahme") | E16: =SUMIFS(Buchungen!$F$4:$F$1003,Buchungen!$B$4:$B$1003,$B16,Buchungen!$C$4:$C$1003,$C16,Buchungen!$G$4:$G$1003,"Ausgabe") | F16: =$D16-$E16 | G16: =IF($D16<=0,0,$F16/$D16) | H16: =$H15+$F16 | I16: =AVERAGE($E14:$E16) | J16: =AVERAGE($F14:$F16) | K16: =Einstellungen!$C$42 | L16: =$K16-$E16 | M16: 13
A17: 46419 | B17: =YEAR($A17) | C17: =MONTH($A17) | D17: =SUMIFS(Buchungen!$F$4:$F$1003,Buchungen!$B$4:$B$1003,$B17,Buchungen!$C$4:$C$1003,$C17,Buchungen!$G$4:$G$1003,"Einnahme") | E17: =SUMIFS(Buchungen!$F$4:$F$1003,Buchungen!$B$4:$B$1003,$B17,Buchungen!$C$4:$C$1003,$C17,Buchungen!$G$4:$G$1003,"Ausgabe") | F17: =$D17-$E17 | G17: =IF($D17<=0,0,$F17/$D17) | H17: =$H16+$F17 | I17: =AVERAGE($E15:$E17) | J17: =AVERAGE($F15:$F17) | K17: =Einstellungen!$C$42 | L17: =$K17-$E17 | M17: 14
... A27: 46722 | B27: =YEAR($A27) | C27: =MONTH($A27) | D27: =SUMIFS(Buchungen!$F$4:$F$1003,Buchungen!$B$4:$B$1003,$B27,Buchungen!$C$4:$C$1003,$C27,Buchungen!$G$4:$G$1003,"Einnahme") | E27: =SUMIFS(Buchungen!$F$4:$F$1003,Buchungen!$B$4:$B$1003,$B27,Buchungen!$C$4:$C$1003,$C27,Buchungen!$G$4:$G$1003,"Ausgabe") | F27: =$D27-$E27 | G27: =IF($D27<=0,0,$F27/$D27) | H27: =$H26+$F27 | I27: =AVERAGE($E25:$E27) | J27: =AVERAGE($F25:$F27) | K27: =Einstellungen!$C$42 | L27: =$K27-$E27 | M27: 24
A29: Gesamt | D29: =SUM(D4:D27) | E29: =SUM(E4:E27) | F29: =SUM(F4:F27) | G29: =IF($D29<=0,0,$F29/$D29)

Sheet Kategorien
A1: Kategorien-Auswertung
A2: Kategorie × Monat für ein Jahr, inklusive Budgetvergleich
A3: Jahr auswählen: | B3: 2026
A4: Hilfszeile → Monatsnummern | C4: 1 | D4: 2 | E4: 3 | F4: 4 | G4: 5 | H4: 6 | I4: 7 | J4: 8 | K4: 9 | L4: 10 | M4: 11 | N4: 12
A5: Kategorie | B5: Typ | C5: Jan | D5: Feb | E5: Mär | F5: Apr | G5: Mai | H5: Jun | I5: Jul | J5: Aug | K5: Sep | L5: Okt | M5: Nov | N5: Dez | O5: Summe (€) | P5: Ø/Monat (€) | Q5: Budget (€) | R5: Abw. Ø (€) | S5: Hilfsspalte
A6: =IF(Einstellungen!$A4="","",Einstellungen!$A4) | B6: =IF(Einstellungen!$B4="","",Einstellungen!$B4) | C6: =IF($A6="",0,SUMIFS(Buchungen!$F$4:$F$1003,Buchungen!$B$4:$B$1003,$B$3,Buchungen!$C$4:$C$1003,C$4,Buchungen!$D$4:$D$1003,$A6)) | D6: =IF($A6="",0,SUMIFS(Buchungen!$F$4:$F$1003,Buchungen!$B$4:$B$1003,$B$3,Buchungen!$C$4:$C$1003,D$4,Buchungen!$D$4:$D$1003,$A6)) | E6: =IF($A6="",0,SUMIFS(Buchungen!$F$4:$F$1003,Buchungen!$B$4:$B$1003,$B$3,Buchungen!$C$4:$C$1003,E$4,Buchungen!$D$4:$D$1003,$A6)) | F6: =IF($A6="",0,SUMIFS(Buchungen!$F$4:$F$1003,Buchungen!$B$4:$B$1003,$B$3,Buchungen!$C$4:$C$1003,F$4,Buchungen!$D$4:$D$1003,$A6)) | G6: =IF($A6="",0,SUMIFS(Buchungen!$F$4:$F$1003,Buchungen!$B$4:$B$1003,$B$3,Buchungen!$C$4:$C$1003,G$4,Buchungen!$D$4:$D$1003,$A6)) | H6: =IF($A6="",0,SUMIFS(Buchungen!$F$4:$F$1003,Buchungen!$B$4:$B$1003,$B$3,Buchungen!$C$4:$C$1003,H$4,Buchungen!$D$4:$D$1003,$A6)) | I6: =IF($A6="",0,SUMIFS(Buchungen!$F$4:$F$1003,Buchungen!$B$4:$B$1003,$B$3,Buchungen!$C$4:$C$1003,I$4,Buchungen!$D$4:$D$1003,$A6)) | J6: =IF($A6="",0,SUMIFS(Buchungen!$F$4:$F$1003,Buchungen!$B$4:$B$1003,$B$3,Buchungen!$C$4:$C$1003,J$4,Buchungen!$D$4:$D$1003,$A6)) | ... N6: =IF($A6="",0,SUMIFS(Buchungen!$F$4:$F$1003,Buchungen!$B$4:$B$1003,$B$3,Buchungen!$C$4:$C$1003,N$4,Buchungen!$D$4:$D$1003,$A6)) | O6: =SUM($C6:$N6) | P6: =IFERROR(AVERAGEIF($C6:$N6,"<>0"),0) | Q6: =IF(Einstellungen!$C4="",0,Einstellungen!$C4) | R6: =$Q6-$P6 | S6: =IF($B6="Ausgabe",$O6,0)
A7: =IF(Einstellungen!$A5="","",Einstellungen!$A5) | B7: =IF(Einstellungen!$B5="","",Einstellungen!$B5) | C7: =IF($A7="",0,SUMIFS(Buchungen!$F$4:$F$1003,Buchungen!$B$4:$B$1003,$B$3,Buchungen!$C$4:$C$1003,C$4,Buchungen!$D$4:$D$1003,$A7)) | D7: =IF($A7="",0,SUMIFS(Buchungen!$F$4:$F$1003,Buchungen!$B$4:$B$1003,$B$3,Buchungen!$C$4:$C$1003,D$4,Buchungen!$D$4:$D$1003,$A7)) | E7: =IF($A7="",0,SUMIFS(Buchungen!$F$4:$F$1003,Buchungen!$B$4:$B$1003,$B$3,Buchungen!$C$4:$C$1003,E$4,Buchungen!$D$4:$D$1003,$A7)) | F7: =IF($A7="",0,SUMIFS(Buchungen!$F$4:$F$1003,Buchungen!$B$4:$B$1003,$B$3,Buchungen!$C$4:$C$1003,F$4,Buchungen!$D$4:$D$1003,$A7)) | G7: =IF($A7="",0,SUMIFS(Buchungen!$F$4:$F$1003,Buchungen!$B$4:$B$1003,$B$3,Buchungen!$C$4:$C$1003,G$4,Buchungen!$D$4:$D$1003,$A7)) | H7: =IF($A7="",0,SUMIFS(Buchungen!$F$4:$F$1003,Buchungen!$B$4:$B$1003,$B$3,Buchungen!$C$4:$C$1003,H$4,Buchungen!$D$4:$D$1003,$A7)) | I7: =IF($A7="",0,SUMIFS(Buchungen!$F$4:$F$1003,Buchungen!$B$4:$B$1003,$B$3,Buchungen!$C$4:$C$1003,I$4,Buchungen!$D$4:$D$1003,$A7)) | J7: =IF($A7="",0,SUMIFS(Buchungen!$F$4:$F$1003,Buchungen!$B$4:$B$1003,$B$3,Buchungen!$C$4:$C$1003,J$4,Buchungen!$D$4:$D$1003,$A7)) | ... N7: =IF($A7="",0,SUMIFS(Buchungen!$F$4:$F$1003,Buchungen!$B$4:$B$1003,$B$3,Buchungen!$C$4:$C$1003,N$4,Buchungen!$D$4:$D$1003,$A7)) | O7: =SUM($C7:$N7) | P7: =IFERROR(AVERAGEIF($C7:$N7,"<>0"),0) | Q7: =IF(Einstellungen!$C5="",0,Einstellungen!$C5) | R7: =$Q7-$P7 | S7: =IF($B7="Ausgabe",$O7,0)
A8: =IF(Einstellungen!$A6="","",Einstellungen!$A6) | B8: =IF(Einstellungen!$B6="","",Einstellungen!$B6) | C8: =IF($A8="",0,SUMIFS(Buchungen!$F$4:$F$1003,Buchungen!$B$4:$B$1003,$B$3,Buchungen!$C$4:$C$1003,C$4,Buchungen!$D$4:$D$1003,$A8)) | D8: =IF($A8="",0,SUMIFS(Buchungen!$F$4:$F$1003,Buchungen!$B$4:$B$1003,$B$3,Buchungen!$C$4:$C$1003,D$4,Buchungen!$D$4:$D$1003,$A8)) | E8: =IF($A8="",0,SUMIFS(Buchungen!$F$4:$F$1003,Buchungen!$B$4:$B$1003,$B$3,Buchungen!$C$4:$C$1003,E$4,Buchungen!$D$4:$D$1003,$A8)) | F8: =IF($A8="",0,SUMIFS(Buchungen!$F$4:$F$1003,Buchungen!$B$4:$B$1003,$B$3,Buchungen!$C$4:$C$1003,F$4,Buchungen!$D$4:$D$1003,$A8)) | G8: =IF($A8="",0,SUMIFS(Buchungen!$F$4:$F$1003,Buchungen!$B$4:$B$1003,$B$3,Buchungen!$C$4:$C$1003,G$4,Buchungen!$D$4:$D$1003,$A8)) | H8: =IF($A8="",0,SUMIFS(Buchungen!$F$4:$F$1003,Buchungen!$B$4:$B$1003,$B$3,Buchungen!$C$4:$C$1003,H$4,Buchungen!$D$4:$D$1003,$A8)) | I8: =IF($A8="",0,SUMIFS(Buchungen!$F$4:$F$1003,Buchungen!$B$4:$B$1003,$B$3,Buchungen!$C$4:$C$1003,I$4,Buchungen!$D$4:$D$1003,$A8)) | J8: =IF($A8="",0,SUMIFS(Buchungen!$F$4:$F$1003,Buchungen!$B$4:$B$1003,$B$3,Buchungen!$C$4:$C$1003,J$4,Buchungen!$D$4:$D$1003,$A8)) | ... N8: =IF($A8="",0,SUMIFS(Buchungen!$F$4:$F$1003,Buchungen!$B$4:$B$1003,$B$3,Buchungen!$C$4:$C$1003,N$4,Buchungen!$D$4:$D$1003,$A8)) | O8: =SUM($C8:$N8) | P8: =IFERROR(AVERAGEIF($C8:$N8,"<>0"),0) | Q8: =IF(Einstellungen!$C6="",0,Einstellungen!$C6) | R8: =$Q8-$P8 | S8: =IF($B8="Ausgabe",$O8,0)
A9: =IF(Einstellungen!$A7="","",Einstellungen!$A7) | B9: =IF(Einstellungen!$B7="","",Einstellungen!$B7) | C9: =IF($A9="",0,SUMIFS(Buchungen!$F$4:$F$1003,Buchungen!$B$4:$B$1003,$B$3,Buchungen!$C$4:$C$1003,C$4,Buchungen!$D$4:$D$1003,$A9)) | D9: =IF($A9="",0,SUMIFS(Buchungen!$F$4:$F$1003,Buchungen!$B$4:$B$1003,$B$3,Buchungen!$C$4:$C$1003,D$4,Buchungen!$D$4:$D$1003,$A9)) | E9: =IF($A9="",0,SUMIFS(Buchungen!$F$4:$F$1003,Buchungen!$B$4:$B$1003,$B$3,Buchungen!$C$4:$C$1003,E$4,Buchungen!$D$4:$D$1003,$A9)) | F9: =IF($A9="",0,SUMIFS(Buchungen!$F$4:$F$1003,Buchungen!$B$4:$B$1003,$B$3,Buchungen!$C$4:$C$1003,F$4,Buchungen!$D$4:$D$1003,$A9)) | G9: =IF($A9="",0,SUMIFS(Buchungen!$F$4:$F$1003,Buchungen!$B$4:$B$1003,$B$3,Buchungen!$C$4:$C$1003,G$4,Buchungen!$D$4:$D$1003,$A9)) | H9: =IF($A9="",0,SUMIFS(Buchungen!$F$4:$F$1003,Buchungen!$B$4:$B$1003,$B$3,Buchungen!$C$4:$C$1003,H$4,Buchungen!$D$4:$D$1003,$A9)) | I9: =IF($A9="",0,SUMIFS(Buchungen!$F$4:$F$1003,Buchungen!$B$4:$B$1003,$B$3,Buchungen!$C$4:$C$1003,I$4,Buchungen!$D$4:$D$1003,$A9)) | J9: =IF($A9="",0,SUMIFS(Buchungen!$F$4:$F$1003,Buchungen!$B$4:$B$1003,$B$3,Buchungen!$C$4:$C$1003,J$4,Buchungen!$D$4:$D$1003,$A9)) | ... N9: =IF($A9="",0,SUMIFS(Buchungen!$F$4:$F$1003,Buchungen!$B$4:$B$1003,$B$3,Buchungen!$C$4:$C$1003,N$4,Buchungen!$D$4:$D$1003,$A9)) | O9: =SUM($C9:$N9) | P9: =IFERROR(AVERAGEIF($C9:$N9,"<>0"),0) | Q9: =IF(Einstellungen!$C7="",0,Einstellungen!$C7) | R9: =$Q9-$P9 | S9: =IF($B9="Ausgabe",$O9,0)
A10: =IF(Einstellungen!$A8="","",Einstellungen!$A8) | B10: =IF(Einstellungen!$B8="","",Einstellungen!$B8) | C10: =IF($A10="",0,SUMIFS(Buchungen!$F$4:$F$1003,Buchungen!$B$4:$B$1003,$B$3,Buchungen!$C$4:$C$1003,C$4,Buchungen!$D$4:$D$1003,$A10)) | D10: =IF($A10="",0,SUMIFS(Buchungen!$F$4:$F$1003,Buchungen!$B$4:$B$1003,$B$3,Buchungen!$C$4:$C$1003,D$4,Buchungen!$D$4:$D$1003,$A10)) | E10: =IF($A10="",0,SUMIFS(Buchungen!$F$4:$F$1003,Buchungen!$B$4:$B$1003,$B$3,Buchungen!$C$4:$C$1003,E$4,Buchungen!$D$4:$D$1003,$A10)) | F10: =IF($A10="",0,SUMIFS(Buchungen!$F$4:$F$1003,Buchungen!$B$4:$B$1003,$B$3,Buchungen!$C$4:$C$1003,F$4,Buchungen!$D$4:$D$1003,$A10)) | G10: =IF($A10="",0,SUMIFS(Buchungen!$F$4:$F$1003,Buchungen!$B$4:$B$1003,$B$3,Buchungen!$C$4:$C$1003,G$4,Buchungen!$D$4:$D$1003,$A10)) | H10: =IF($A10="",0,SUMIFS(Buchungen!$F$4:$F$1003,Buchungen!$B$4:$B$1003,$B$3,Buchungen!$C$4:$C$1003,H$4,Buchungen!$D$4:$D$1003,$A10)) | I10: =IF($A10="",0,SUMIFS(Buchungen!$F$4:$F$1003,Buchungen!$B$4:$B$1003,$B$3,Buchungen!$C$4:$C$1003,I$4,Buchungen!$D$4:$D$1003,$A10)) | J10: =IF($A10="",0,SUMIFS(Buchungen!$F$4:$F$1003,Buchungen!$B$4:$B$1003,$B$3,Buchungen!$C$4:$C$1003,J$4,Buchungen!$D$4:$D$1003,$A10)) | ... N10: =IF($A10="",0,SUMIFS(Buchungen!$F$4:$F$1003,Buchungen!$B$4:$B$1003,$B$3,Buchungen!$C$4:$C$1003,N$4,Buchungen!$D$4:$D$1003,$A10)) | O10: =SUM($C10:$N10) | P10: =IFERROR(AVERAGEIF($C10:$N10,"<>0"),0) | Q10: =IF(Einstellungen!$C8="",0,Einstellungen!$C8) | R10: =$Q10-$P10 | S10: =IF($B10="Ausgabe",$O10,0)
A11: =IF(Einstellungen!$A9="","",Einstellungen!$A9) | B11: =IF(Einstellungen!$B9="","",Einstellungen!$B9) | C11: =IF($A11="",0,SUMIFS(Buchungen!$F$4:$F$1003,Buchungen!$B$4:$B$1003,$B$3,Buchungen!$C$4:$C$1003,C$4,Buchungen!$D$4:$D$1003,$A11)) | D11: =IF($A11="",0,SUMIFS(Buchungen!$F$4:$F$1003,Buchungen!$B$4:$B$1003,$B$3,Buchungen!$C$4:$C$1003,D$4,Buchungen!$D$4:$D$1003,$A11)) | E11: =IF($A11="",0,SUMIFS(Buchungen!$F$4:$F$1003,Buchungen!$B$4:$B$1003,$B$3,Buchungen!$C$4:$C$1003,E$4,Buchungen!$D$4:$D$1003,$A11)) | F11: =IF($A11="",0,SUMIFS(Buchungen!$F$4:$F$1003,Buchungen!$B$4:$B$1003,$B$3,Buchungen!$C$4:$C$1003,F$4,Buchungen!$D$4:$D$1003,$A11)) | G11: =IF($A11="",0,SUMIFS(Buchungen!$F$4:$F$1003,Buchungen!$B$4:$B$1003,$B$3,Buchungen!$C$4:$C$1003,G$4,Buchungen!$D$4:$D$1003,$A11)) | H11: =IF($A11="",0,SUMIFS(Buchungen!$F$4:$F$1003,Buchungen!$B$4:$B$1003,$B$3,Buchungen!$C$4:$C$1003,H$4,Buchungen!$D$4:$D$1003,$A11)) | I11: =IF($A11="",0,SUMIFS(Buchungen!$F$4:$F$1003,Buchungen!$B$4:$B$1003,$B$3,Buchungen!$C$4:$C$1003,I$4,Buchungen!$D$4:$D$1003,$A11)) | J11: =IF($A11="",0,SUMIFS(Buchungen!$F$4:$F$1003,Buchungen!$B$4:$B$1003,$B$3,Buchungen!$C$4:$C$1003,J$4,Buchungen!$D$4:$D$1003,$A11)) | ... N11: =IF($A11="",0,SUMIFS(Buchungen!$F$4:$F$1003,Buchungen!$B$4:$B$1003,$B$3,Buchungen!$C$4:$C$1003,N$4,Buchungen!$D$4:$D$1003,$A11)) | O11: =SUM($C11:$N11) | P11: =IFERROR(AVERAGEIF($C11:$N11,"<>0"),0) | Q11: =IF(Einstellungen!$C9="",0,Einstellungen!$C9) | R11: =$Q11-$P11 | S11: =IF($B11="Ausgabe",$O11,0)
A12: =IF(Einstellungen!$A10="","",Einstellungen!$A10) | B12: =IF(Einstellungen!$B10="","",Einstellungen!$B10) | C12: =IF($A12="",0,SUMIFS(Buchungen!$F$4:$F$1003,Buchungen!$B$4:$B$1003,$B$3,Buchungen!$C$4:$C$1003,C$4,Buchungen!$D$4:$D$1003,$A12)) | D12: =IF($A12="",0,SUMIFS(Buchungen!$F$4:$F$1003,Buchungen!$B$4:$B$1003,$B$3,Buchungen!$C$4:$C$1003,D$4,Buchungen!$D$4:$D$1003,$A12)) | E12: =IF($A12="",0,SUMIFS(Buchungen!$F$4:$F$1003,Buchungen!$B$4:$B$1003,$B$3,Buchungen!$C$4:$C$1003,E$4,Buchungen!$D$4:$D$1003,$A12)) | F12: =IF($A12="",0,SUMIFS(Buchungen!$F$4:$F$1003,Buchungen!$B$4:$B$1003,$B$3,Buchungen!$C$4:$C$1003,F$4,Buchungen!$D$4:$D$1003,$A12)) | G12: =IF($A12="",0,SUMIFS(Buchungen!$F$4:$F$1003,Buchungen!$B$4:$B$1003,$B$3,Buchungen!$C$4:$C$1003,G$4,Buchungen!$D$4:$D$1003,$A12)) | H12: =IF($A12="",0,SUMIFS(Buchungen!$F$4:$F$1003,Buchungen!$B$4:$B$1003,$B$3,Buchungen!$C$4:$C$1003,H$4,Buchungen!$D$4:$D$1003,$A12)) | I12: =IF($A12="",0,SUMIFS(Buchungen!$F$4:$F$1003,Buchungen!$B$4:$B$1003,$B$3,Buchungen!$C$4:$C$1003,I$4,Buchungen!$D$4:$D$1003,$A12)) | J12: =IF($A12="",0,SUMIFS(Buchungen!$F$4:$F$1003,Buchungen!$B$4:$B$1003,$B$3,Buchungen!$C$4:$C$1003,J$4,Buchungen!$D$4:$D$1003,$A12)) | ... N12: =IF($A12="",0,SUMIFS(Buchungen!$F$4:$F$1003,Buchungen!$B$4:$B$1003,$B$3,Buchungen!$C$4:$C$1003,N$4,Buchungen!$D$4:$D$1003,$A12)) | O12: =SUM($C12:$N12) | P12: =IFERROR(AVERAGEIF($C12:$N12,"<>0"),0) | Q12: =IF(Einstellungen!$C10="",0,Einstellungen!$C10) | R12: =$Q12-$P12 | S12: =IF($B12="Ausgabe",$O12,0)
A13: =IF(Einstellungen!$A11="","",Einstellungen!$A11) | B13: =IF(Einstellungen!$B11="","",Einstellungen!$B11) | C13: =IF($A13="",0,SUMIFS(Buchungen!$F$4:$F$1003,Buchungen!$B$4:$B$1003,$B$3,Buchungen!$C$4:$C$1003,C$4,Buchungen!$D$4:$D$1003,$A13)) | D13: =IF($A13="",0,SUMIFS(Buchungen!$F$4:$F$1003,Buchungen!$B$4:$B$1003,$B$3,Buchungen!$C$4:$C$1003,D$4,Buchungen!$D$4:$D$1003,$A13)) | E13: =IF($A13="",0,SUMIFS(Buchungen!$F$4:$F$1003,Buchungen!$B$4:$B$1003,$B$3,Buchungen!$C$4:$C$1003,E$4,Buchungen!$D$4:$D$1003,$A13)) | F13: =IF($A13="",0,SUMIFS(Buchungen!$F$4:$F$1003,Buchungen!$B$4:$B$1003,$B$3,Buchungen!$C$4:$C$1003,F$4,Buchungen!$D$4:$D$1003,$A13)) | G13: =IF($A13="",0,SUMIFS(Buchungen!$F$4:$F$1003,Buchungen!$B$4:$B$1003,$B$3,Buchungen!$C$4:$C$1003,G$4,Buchungen!$D$4:$D$1003,$A13)) | H13: =IF($A13="",0,SUMIFS(Buchungen!$F$4:$F$1003,Buchungen!$B$4:$B$1003,$B$3,Buchungen!$C$4:$C$1003,H$4,Buchungen!$D$4:$D$1003,$A13)) | I13: =IF($A13="",0,SUMIFS(Buchungen!$F$4:$F$1003,Buchungen!$B$4:$B$1003,$B$3,Buchungen!$C$4:$C$1003,I$4,Buchungen!$D$4:$D$1003,$A13)) | J13: =IF($A13="",0,SUMIFS(Buchungen!$F$4:$F$1003,Buchungen!$B$4:$B$1003,$B$3,Buchungen!$C$4:$C$1003,J$4,Buchungen!$D$4:$D$1003,$A13)) | ... N13: =IF($A13="",0,SUMIFS(Buchungen!$F$4:$F$1003,Buchungen!$B$4:$B$1003,$B$3,Buchungen!$C$4:$C$1003,N$4,Buchungen!$D$4:$D$1003,$A13)) | O13: =SUM($C13:$N13) | P13: =IFERROR(AVERAGEIF($C13:$N13,"<>0"),0) | Q13: =IF(Einstellungen!$C11="",0,Einstellungen!$C11) | R13: =$Q13-$P13 | S13: =IF($B13="Ausgabe",$O13,0)
A14: =IF(Einstellungen!$A12="","",Einstellungen!$A12) | B14: =IF(Einstellungen!$B12="","",Einstellungen!$B12) | C14: =IF($A14="",0,SUMIFS(Buchungen!$F$4:$F$1003,Buchungen!$B$4:$B$1003,$B$3,Buchungen!$C$4:$C$1003,C$4,Buchungen!$D$4:$D$1003,$A14)) | D14: =IF($A14="",0,SUMIFS(Buchungen!$F$4:$F$1003,Buchungen!$B$4:$B$1003,$B$3,Buchungen!$C$4:$C$1003,D$4,Buchungen!$D$4:$D$1003,$A14)) | E14: =IF($A14="",0,SUMIFS(Buchungen!$F$4:$F$1003,Buchungen!$B$4:$B$1003,$B$3,Buchungen!$C$4:$C$1003,E$4,Buchungen!$D$4:$D$1003,$A14)) | F14: =IF($A14="",0,SUMIFS(Buchungen!$F$4:$F$1003,Buchungen!$B$4:$B$1003,$B$3,Buchungen!$C$4:$C$1003,F$4,Buchungen!$D$4:$D$1003,$A14)) | G14: =IF($A14="",0,SUMIFS(Buchungen!$F$4:$F$1003,Buchungen!$B$4:$B$1003,$B$3,Buchungen!$C$4:$C$1003,G$4,Buchungen!$D$4:$D$1003,$A14)) | H14: =IF($A14="",0,SUMIFS(Buchungen!$F$4:$F$1003,Buchungen!$B$4:$B$1003,$B$3,Buchungen!$C$4:$C$1003,H$4,Buchungen!$D$4:$D$1003,$A14)) | I14: =IF($A14="",0,SUMIFS(Buchungen!$F$4:$F$1003,Buchungen!$B$4:$B$1003,$B$3,Buchungen!$C$4:$C$1003,I$4,Buchungen!$D$4:$D$1003,$A14)) | J14: =IF($A14="",0,SUMIFS(Buchungen!$F$4:$F$1003,Buchungen!$B$4:$B$1003,$B$3,Buchungen!$C$4:$C$1003,J$4,Buchungen!$D$4:$D$1003,$A14)) | ... N14: =IF($A14="",0,SUMIFS(Buchungen!$F$4:$F$1003,Buchungen!$B$4:$B$1003,$B$3,Buchungen!$C$4:$C$1003,N$4,Buchungen!$D$4:$D$1003,$A14)) | O14: =SUM($C14:$N14) | P14: =IFERROR(AVERAGEIF($C14:$N14,"<>0"),0) | Q14: =IF(Einstellungen!$C12="",0,Einstellungen!$C12) | R14: =$Q14-$P14 | S14: =IF($B14="Ausgabe",$O14,0)
A15: =IF(Einstellungen!$A13="","",Einstellungen!$A13) | B15: =IF(Einstellungen!$B13="","",Einstellungen!$B13) | C15: =IF($A15="",0,SUMIFS(Buchungen!$F$4:$F$1003,Buchungen!$B$4:$B$1003,$B$3,Buchungen!$C$4:$C$1003,C$4,Buchungen!$D$4:$D$1003,$A15)) | D15: =IF($A15="",0,SUMIFS(Buchungen!$F$4:$F$1003,Buchungen!$B$4:$B$1003,$B$3,Buchungen!$C$4:$C$1003,D$4,Buchungen!$D$4:$D$1003,$A15)) | E15: =IF($A15="",0,SUMIFS(Buchungen!$F$4:$F$1003,Buchungen!$B$4:$B$1003,$B$3,Buchungen!$C$4:$C$1003,E$4,Buchungen!$D$4:$D$1003,$A15)) | F15: =IF($A15="",0,SUMIFS(Buchungen!$F$4:$F$1003,Buchungen!$B$4:$B$1003,$B$3,Buchungen!$C$4:$C$1003,F$4,Buchungen!$D$4:$D$1003,$A15)) | G15: =IF($A15="",0,SUMIFS(Buchungen!$F$4:$F$1003,Buchungen!$B$4:$B$1003,$B$3,Buchungen!$C$4:$C$1003,G$4,Buchungen!$D$4:$D$1003,$A15)) | H15: =IF($A15="",0,SUMIFS(Buchungen!$F$4:$F$1003,Buchungen!$B$4:$B$1003,$B$3,Buchungen!$C$4:$C$1003,H$4,Buchungen!$D$4:$D$1003,$A15)) | I15: =IF($A15="",0,SUMIFS(Buchungen!$F$4:$F$1003,Buchungen!$B$4:$B$1003,$B$3,Buchungen!$C$4:$C$1003,I$4,Buchungen!$D$4:$D$1003,$A15)) | J15: =IF($A15="",0,SUMIFS(Buchungen!$F$4:$F$1003,Buchungen!$B$4:$B$1003,$B$3,Buchungen!$C$4:$C$1003,J$4,Buchungen!$D$4:$D$1003,$A15)) | ... N15: =IF($A15="",0,SUMIFS(Buchungen!$F$4:$F$1003,Buchungen!$B$4:$B$1003,$B$3,Buchungen!$C$4:$C$1003,N$4,Buchungen!$D$4:$D$1003,$A15)) | O15: =SUM($C15:$N15) | P15: =IFERROR(AVERAGEIF($C15:$N15,"<>0"),0) | Q15: =IF(Einstellungen!$C13="",0,Einstellungen!$C13) | R15: =$Q15-$P15 | S15: =IF($B15="Ausgabe",$O15,0)
A16: =IF(Einstellungen!$A14="","",Einstellungen!$A14) | B16: =IF(Einstellungen!$B14="","",Einstellungen!$B14) | C16: =IF($A16="",0,SUMIFS(Buchungen!$F$4:$F$1003,Buchungen!$B$4:$B$1003,$B$3,Buchungen!$C$4:$C$1003,C$4,Buchungen!$D$4:$D$1003,$A16)) | D16: =IF($A16="",0,SUMIFS(Buchungen!$F$4:$F$1003,Buchungen!$B$4:$B$1003,$B$3,Buchungen!$C$4:$C$1003,D$4,Buchungen!$D$4:$D$1003,$A16)) | E16: =IF($A16="",0,SUMIFS(Buchungen!$F$4:$F$1003,Buchungen!$B$4:$B$1003,$B$3,Buchungen!$C$4:$C$1003,E$4,Buchungen!$D$4:$D$1003,$A16)) | F16: =IF($A16="",0,SUMIFS(Buchungen!$F$4:$F$1003,Buchungen!$B$4:$B$1003,$B$3,Buchungen!$C$4:$C$1003,F$4,Buchungen!$D$4:$D$1003,$A16)) | G16: =IF($A16="",0,SUMIFS(Buchungen!$F$4:$F$1003,Buchungen!$B$4:$B$1003,$B$3,Buchungen!$C$4:$C$1003,G$4,Buchungen!$D$4:$D$1003,$A16)) | H16: =IF($A16="",0,SUMIFS(Buchungen!$F$4:$F$1003,Buchungen!$B$4:$B$1003,$B$3,Buchungen!$C$4:$C$1003,H$4,Buchungen!$D$4:$D$1003,$A16)) | I16: =IF($A16="",0,SUMIFS(Buchungen!$F$4:$F$1003,Buchungen!$B$4:$B$1003,$B$3,Buchungen!$C$4:$C$1003,I$4,Buchungen!$D$4:$D$1003,$A16)) | J16: =IF($A16="",0,SUMIFS(Buchungen!$F$4:$F$1003,Buchungen!$B$4:$B$1003,$B$3,Buchungen!$C$4:$C$1003,J$4,Buchungen!$D$4:$D$1003,$A16)) | ... N16: =IF($A16="",0,SUMIFS(Buchungen!$F$4:$F$1003,Buchungen!$B$4:$B$1003,$B$3,Buchungen!$C$4:$C$1003,N$4,Buchungen!$D$4:$D$1003,$A16)) | O16: =SUM($C16:$N16) | P16: =IFERROR(AVERAGEIF($C16:$N16,"<>0"),0) | Q16: =IF(Einstellungen!$C14="",0,Einstellungen!$C14) | R16: =$Q16-$P16 | S16: =IF($B16="Ausgabe",$O16,0)
A17: =IF(Einstellungen!$A15="","",Einstellungen!$A15) | B17: =IF(Einstellungen!$B15="","",Einstellungen!$B15) | C17: =IF($A17="",0,SUMIFS(Buchungen!$F$4:$F$1003,Buchungen!$B$4:$B$1003,$B$3,Buchungen!$C$4:$C$1003,C$4,Buchungen!$D$4:$D$1003,$A17)) | D17: =IF($A17="",0,SUMIFS(Buchungen!$F$4:$F$1003,Buchungen!$B$4:$B$1003,$B$3,Buchungen!$C$4:$C$1003,D$4,Buchungen!$D$4:$D$1003,$A17)) | E17: =IF($A17="",0,SUMIFS(Buchungen!$F$4:$F$1003,Buchungen!$B$4:$B$1003,$B$3,Buchungen!$C$4:$C$1003,E$4,Buchungen!$D$4:$D$1003,$A17)) | F17: =IF($A17="",0,SUMIFS(Buchungen!$F$4:$F$1003,Buchungen!$B$4:$B$1003,$B$3,Buchungen!$C$4:$C$1003,F$4,Buchungen!$D$4:$D$1003,$A17)) | G17: =IF($A17="",0,SUMIFS(Buchungen!$F$4:$F$1003,Buchungen!$B$4:$B$1003,$B$3,Buchungen!$C$4:$C$1003,G$4,Buchungen!$D$4:$D$1003,$A17)) | H17: =IF($A17="",0,SUMIFS(Buchungen!$F$4:$F$1003,Buchungen!$B$4:$B$1003,$B$3,Buchungen!$C$4:$C$1003,H$4,Buchungen!$D$4:$D$1003,$A17)) | I17: =IF($A17="",0,SUMIFS(Buchungen!$F$4:$F$1003,Buchungen!$B$4:$B$1003,$B$3,Buchungen!$C$4:$C$1003,I$4,Buchungen!$D$4:$D$1003,$A17)) | J17: =IF($A17="",0,SUMIFS(Buchungen!$F$4:$F$1003,Buchungen!$B$4:$B$1003,$B$3,Buchungen!$C$4:$C$1003,J$4,Buchungen!$D$4:$D$1003,$A17)) | ... N17: =IF($A17="",0,SUMIFS(Buchungen!$F$4:$F$1003,Buchungen!$B$4:$B$1003,$B$3,Buchungen!$C$4:$C$1003,N$4,Buchungen!$D$4:$D$1003,$A17)) | O17: =SUM($C17:$N17) | P17: =IFERROR(AVERAGEIF($C17:$N17,"<>0"),0) | Q17: =IF(Einstellungen!$C15="",0,Einstellungen!$C15) | R17: =$Q17-$P17 | S17: =IF($B17="Ausgabe",$O17,0)
... A42: =IF(Einstellungen!$A40="","",Einstellungen!$A40) | B42: =IF(Einstellungen!$B40="","",Einstellungen!$B40) | C42: =IF($A42="",0,SUMIFS(Buchungen!$F$4:$F$1003,Buchungen!$B$4:$B$1003,$B$3,Buchungen!$C$4:$C$1003,C$4,Buchungen!$D$4:$D$1003,$A42)) | D42: =IF($A42="",0,SUMIFS(Buchungen!$F$4:$F$1003,Buchungen!$B$4:$B$1003,$B$3,Buchungen!$C$4:$C$1003,D$4,Buchungen!$D$4:$D$1003,$A42)) | E42: =IF($A42="",0,SUMIFS(Buchungen!$F$4:$F$1003,Buchungen!$B$4:$B$1003,$B$3,Buchungen!$C$4:$C$1003,E$4,Buchungen!$D$4:$D$1003,$A42)) | F42: =IF($A42="",0,SUMIFS(Buchungen!$F$4:$F$1003,Buchungen!$B$4:$B$1003,$B$3,Buchungen!$C$4:$C$1003,F$4,Buchungen!$D$4:$D$1003,$A42)) | G42: =IF($A42="",0,SUMIFS(Buchungen!$F$4:$F$1003,Buchungen!$B$4:$B$1003,$B$3,Buchungen!$C$4:$C$1003,G$4,Buchungen!$D$4:$D$1003,$A42)) | H42: =IF($A42="",0,SUMIFS(Buchungen!$F$4:$F$1003,Buchungen!$B$4:$B$1003,$B$3,Buchungen!$C$4:$C$1003,H$4,Buchungen!$D$4:$D$1003,$A42)) | I42: =IF($A42="",0,SUMIFS(Buchungen!$F$4:$F$1003,Buchungen!$B$4:$B$1003,$B$3,Buchungen!$C$4:$C$1003,I$4,Buchungen!$D$4:$D$1003,$A42)) | J42: =IF($A42="",0,SUMIFS(Buchungen!$F$4:$F$1003,Buchungen!$B$4:$B$1003,$B$3,Buchungen!$C$4:$C$1003,J$4,Buchungen!$D$4:$D$1003,$A42)) | ... N42: =IF($A42="",0,SUMIFS(Buchungen!$F$4:$F$1003,Buchungen!$B$4:$B$1003,$B$3,Buchungen!$C$4:$C$1003,N$4,Buchungen!$D$4:$D$1003,$A42)) | O42: =SUM($C42:$N42) | P42: =IFERROR(AVERAGEIF($C42:$N42,"<>0"),0) | Q42: =IF(Einstellungen!$C40="",0,Einstellungen!$C40) | R42: =$Q42-$P42 | S42: =IF($B42="Ausgabe",$O42,0)
A44: Gesamt | C44: =SUM(C6:C42) | D44: =SUM(D6:D42) | E44: =SUM(E6:E42) | F44: =SUM(F6:F42) | G44: =SUM(G6:G42) | H44: =SUM(H6:H42) | I44: =SUM(I6:I42) | J44: =SUM(J6:J42) | ... O44: =SUM(O6:O42)
A46: Die Hilfsspalte S blendet Einnahmen aus, damit das Dashboard die größte Ausgabenkategorie findet.

Sheet Sparziele
A1: Sparziele
A2: Zielbetrag und monatliche Rate eintragen – Rest wird berechnet
A3: Ziel | B3: Zielbetrag (€) | C3: Bereits gespart (€) | D3: Monatliche Rate (€) | E3: Fortschritt | F3: Noch offen (€) | G3: Monate bis Ziel | H3: Vorauss. erreicht | I3: Notiz
A4: BEISPIEL – Notgroschen 3 Monatsausgaben | B4: 4500 | C4: 1200 | D4: 250 | E4: =IF(OR($B4="",$B4<=0),"",MIN(1,$C4/$B4)) | F4: =IF($B4="","",MAX(0,$B4-$C4)) | G4: =IF(OR($D4="",$D4<=0,$B4=""),"",IF($F4<=0,0,ROUNDUP($F4/$D4,0))) | H4: =IF($G4="","",EDATE(TODAY(),$G4)) | I4: Beispielzeile – bitte überschreiben
E5: =IF(OR($B5="",$B5<=0),"",MIN(1,$C5/$B5)) | F5: =IF($B5="","",MAX(0,$B5-$C5)) | G5: =IF(OR($D5="",$D5<=0,$B5=""),"",IF($F5<=0,0,ROUNDUP($F5/$D5,0))) | H5: =IF($G5="","",EDATE(TODAY(),$G5))
E6: =IF(OR($B6="",$B6<=0),"",MIN(1,$C6/$B6)) | F6: =IF($B6="","",MAX(0,$B6-$C6)) | G6: =IF(OR($D6="",$D6<=0,$B6=""),"",IF($F6<=0,0,ROUNDUP($F6/$D6,0))) | H6: =IF($G6="","",EDATE(TODAY(),$G6))
E7: =IF(OR($B7="",$B7<=0),"",MIN(1,$C7/$B7)) | F7: =IF($B7="","",MAX(0,$B7-$C7)) | G7: =IF(OR($D7="",$D7<=0,$B7=""),"",IF($F7<=0,0,ROUNDUP($F7/$D7,0))) | H7: =IF($G7="","",EDATE(TODAY(),$G7))
E8: =IF(OR($B8="",$B8<=0),"",MIN(1,$C8/$B8)) | F8: =IF($B8="","",MAX(0,$B8-$C8)) | G8: =IF(OR($D8="",$D8<=0,$B8=""),"",IF($F8<=0,0,ROUNDUP($F8/$D8,0))) | H8: =IF($G8="","",EDATE(TODAY(),$G8))
E9: =IF(OR($B9="",$B9<=0),"",MIN(1,$C9/$B9)) | F9: =IF($B9="","",MAX(0,$B9-$C9)) | G9: =IF(OR($D9="",$D9<=0,$B9=""),"",IF($F9<=0,0,ROUNDUP($F9/$D9,0))) | H9: =IF($G9="","",EDATE(TODAY(),$G9))
E10: =IF(OR($B10="",$B10<=0),"",MIN(1,$C10/$B10)) | F10: =IF($B10="","",MAX(0,$B10-$C10)) | G10: =IF(OR($D10="",$D10<=0,$B10=""),"",IF($F10<=0,0,ROUNDUP($F10/$D10,0))) | H10: =IF($G10="","",EDATE(TODAY(),$G10))
E11: =IF(OR($B11="",$B11<=0),"",MIN(1,$C11/$B11)) | F11: =IF($B11="","",MAX(0,$B11-$C11)) | G11: =IF(OR($D11="",$D11<=0,$B11=""),"",IF($F11<=0,0,ROUNDUP($F11/$D11,0))) | H11: =IF($G11="","",EDATE(TODAY(),$G11))
E12: =IF(OR($B12="",$B12<=0),"",MIN(1,$C12/$B12)) | F12: =IF($B12="","",MAX(0,$B12-$C12)) | G12: =IF(OR($D12="",$D12<=0,$B12=""),"",IF($F12<=0,0,ROUNDUP($F12/$D12,0))) | H12: =IF($G12="","",EDATE(TODAY(),$G12))
E13: =IF(OR($B13="",$B13<=0),"",MIN(1,$C13/$B13)) | F13: =IF($B13="","",MAX(0,$B13-$C13)) | G13: =IF(OR($D13="",$D13<=0,$B13=""),"",IF($F13<=0,0,ROUNDUP($F13/$D13,0))) | H13: =IF($G13="","",EDATE(TODAY(),$G13))
E14: =IF(OR($B14="",$B14<=0),"",MIN(1,$C14/$B14)) | F14: =IF($B14="","",MAX(0,$B14-$C14)) | G14: =IF(OR($D14="",$D14<=0,$B14=""),"",IF($F14<=0,0,ROUNDUP($F14/$D14,0))) | H14: =IF($G14="","",EDATE(TODAY(),$G14))
E15: =IF(OR($B15="",$B15<=0),"",MIN(1,$C15/$B15)) | F15: =IF($B15="","",MAX(0,$B15-$C15)) | G15: =IF(OR($D15="",$D15<=0,$B15=""),"",IF($F15<=0,0,ROUNDUP($F15/$D15,0))) | H15: =IF($G15="","",EDATE(TODAY(),$G15))
E16: =IF(OR($B16="",$B16<=0),"",MIN(1,$C16/$B16)) | F16: =IF($B16="","",MAX(0,$B16-$C16)) | G16: =IF(OR($D16="",$D16<=0,$B16=""),"",IF($F16<=0,0,ROUNDUP($F16/$D16,0))) | H16: =IF($G16="","",EDATE(TODAY(),$G16))
... E18: =IF(OR($B18="",$B18<=0),"",MIN(1,$C18/$B18)) | F18: =IF($B18="","",MAX(0,$B18-$C18)) | G18: =IF(OR($D18="",$D18<=0,$B18=""),"",IF($F18<=0,0,ROUNDUP($F18/$D18,0))) | H18: =IF($G18="","",EDATE(TODAY(),$G18))

Sheet Vermögen
A1: Vermögensentwicklung
A2: Einmal pro Monat die Kontostände eintragen (blaue/gelbe Spalten)
A3: Monat | B3: Girokonto S-POOL (€) | C3: Tagesgeld (€) | D3: Depot (€) | E3: Bargeld (€) | F3: Gemeinschaftskonto (€) | G3: Summe Aktiva (€) | H3: Kreditkarte / Schulden (€) | I3: Nettovermögen (€) | J3: Veränderung (€) | K3: Ø Veränderung 3M (€)
A4: =Monatsübersicht!$A4 | G4: =SUM($B4:$F4) | I4: =$G4-$H4
A5: =Monatsübersicht!$A5 | G5: =SUM($B5:$F5) | I5: =$G5-$H5 | J5: =$I5-$I4
A6: =Monatsübersicht!$A6 | G6: =SUM($B6:$F6) | I6: =$G6-$H6 | J6: =$I6-$I5
A7: =Monatsübersicht!$A7 | G7: =SUM($B7:$F7) | I7: =$G7-$H7 | J7: =$I7-$I6 | K7: =AVERAGE($J5:$J7)
A8: =Monatsübersicht!$A8 | G8: =SUM($B8:$F8) | I8: =$G8-$H8 | J8: =$I8-$I7 | K8: =AVERAGE($J6:$J8)
A9: =Monatsübersicht!$A9 | G9: =SUM($B9:$F9) | I9: =$G9-$H9 | J9: =$I9-$I8 | K9: =AVERAGE($J7:$J9)
A10: =Monatsübersicht!$A10 | G10: =SUM($B10:$F10) | I10: =$G10-$H10 | J10: =$I10-$I9 | K10: =AVERAGE($J8:$J10)
A11: =Monatsübersicht!$A11 | B11: 64.23 | C11: 0 | F11: 62.36 | G11: =SUM($B11:$F11) | H11: 522.74 | I11: =$G11-$H11 | J11: =$I11-$I10 | K11: =AVERAGE($J9:$J11) | L11: Kontostände laut Sparkassen-Finanzübersicht vom 18.08.2026 (von Sarah bereitgestellt)
A12: =Monatsübersicht!$A12 | G12: =SUM($B12:$F12) | I12: =$G12-$H12 | J12: =$I12-$I11 | K12: =AVERAGE($J10:$J12)
A13: =Monatsübersicht!$A13 | G13: =SUM($B13:$F13) | I13: =$G13-$H13 | J13: =$I13-$I12 | K13: =AVERAGE($J11:$J13)
A14: =Monatsübersicht!$A14 | G14: =SUM($B14:$F14) | I14: =$G14-$H14 | J14: =$I14-$I13 | K14: =AVERAGE($J12:$J14)
A15: =Monatsübersicht!$A15 | G15: =SUM($B15:$F15) | I15: =$G15-$H15 | J15: =$I15-$I14 | K15: =AVERAGE($J13:$J15)
A16: =Monatsübersicht!$A16 | G16: =SUM($B16:$F16) | I16: =$G16-$H16 | J16: =$I16-$I15 | K16: =AVERAGE($J14:$J16)
A17: =Monatsübersicht!$A17 | G17: =SUM($B17:$F17) | I17: =$G17-$H17 | J17: =$I17-$I16 | K17: =AVERAGE($J15:$J17)
A18: =Monatsübersicht!$A18 | G18: =SUM($B18:$F18) | I18: =$G18-$H18 | J18: =$I18-$I17 | K18: =AVERAGE($J16:$J18)
A19: =Monatsübersicht!$A19 | G19: =SUM($B19:$F19) | I19: =$G19-$H19 | J19: =$I19-$I18 | K19: =AVERAGE($J17:$J19)
A20: =Monatsübersicht!$A20 | G20: =SUM($B20:$F20) | I20: =$G20-$H20 | J20: =$I20-$I19 | K20: =AVERAGE($J18:$J20)
A21: =Monatsübersicht!$A21 | G21: =SUM($B21:$F21) | I21: =$G21-$H21 | J21: =$I21-$I20 | K21: =AVERAGE($J19:$J21)
A22: =Monatsübersicht!$A22 | G22: =SUM($B22:$F22) | I22: =$G22-$H22 | J22: =$I22-$I21 | K22: =AVERAGE($J20:$J22)
A23: =Monatsübersicht!$A23 | G23: =SUM($B23:$F23) | I23: =$G23-$H23 | J23: =$I23-$I22 | K23: =AVERAGE($J21:$J23)
... A27: =Monatsübersicht!$A27 | G27: =SUM($B27:$F27) | I27: =$G27-$H27 | J27: =$I27-$I26 | K27: =AVERAGE($J25:$J27)
A29: Schulden bitte als positive Zahl eintragen (z. B. offener Kreditbetrag) – sie werden automatisch abgezogen.

Sheet Prognose
A1: Prognose
A2: Hochrechnung der nächsten 12 Monate – aussagekräftig ab ca. 3–6 Monaten echter Daten
A4: Basiswerte (berechnet)
A5: Aktuelles Nettovermögen (€) | B5: =IFERROR(LOOKUP(9.99999999999999E+307,Vermögen!$I$4:$I$27),0)
A6: Ø monatliche Sparrate (Monate mit Daten) | B6: =IFERROR(AVERAGEIF(Monatsübersicht!$F$4:$F$27,"<>0"),0)
A7: Ø monatliche Ausgaben (Monate mit Daten) | B7: =IFERROR(AVERAGEIF(Monatsübersicht!$E$4:$E$27,"<>0"),0)
A8: Ausgaben-Trend pro Monat (linear, €) | B8: =IFERROR(SLOPE(Monatsübersicht!$E$4:$E$27,Monatsübersicht!$M$4:$M$27),0)
A10: Annahmen (anpassbar)
A11: Erwartete Rendite p. a. | B11: 0.02 | F11: Annahme von Claude gesetzt: 2 % p. a. als neutraler Platzhalter – bitte durch deinen eigenen Erwartungswert ersetzen.
A12: Zusätzliche Sparrate pro Monat (€) | B12: 0
A13: Effektive Sparrate (€) | B13: =$B$6+$B$12
A16: Monat n | B16: Datum | C16: Prognose Nettovermögen (€) | D16: Prognose Ausgaben (€)
A17: 0 | B17: =EDATE(TODAY(),$A17) | C17: =IF($B$11=0,$B$5+$B$13*$A17,$B$5*(1+$B$11/12)^$A17+$B$13*(((1+$B$11/12)^$A17-1)/($B$11/12))) | D17: =MAX(0,$B$7+$B$8*$A17)
A18: 1 | B18: =EDATE(TODAY(),$A18) | C18: =IF($B$11=0,$B$5+$B$13*$A18,$B$5*(1+$B$11/12)^$A18+$B$13*(((1+$B$11/12)^$A18-1)/($B$11/12))) | D18: =MAX(0,$B$7+$B$8*$A18)
A19: 2 | B19: =EDATE(TODAY(),$A19) | C19: =IF($B$11=0,$B$5+$B$13*$A19,$B$5*(1+$B$11/12)^$A19+$B$13*(((1+$B$11/12)^$A19-1)/($B$11/12))) | D19: =MAX(0,$B$7+$B$8*$A19)
A20: 3 | B20: =EDATE(TODAY(),$A20) | C20: =IF($B$11=0,$B$5+$B$13*$A20,$B$5*(1+$B$11/12)^$A20+$B$13*(((1+$B$11/12)^$A20-1)/($B$11/12))) | D20: =MAX(0,$B$7+$B$8*$A20)
A21: 4 | B21: =EDATE(TODAY(),$A21) | C21: =IF($B$11=0,$B$5+$B$13*$A21,$B$5*(1+$B$11/12)^$A21+$B$13*(((1+$B$11/12)^$A21-1)/($B$11/12))) | D21: =MAX(0,$B$7+$B$8*$A21)
A22: 5 | B22: =EDATE(TODAY(),$A22) | C22: =IF($B$11=0,$B$5+$B$13*$A22,$B$5*(1+$B$11/12)^$A22+$B$13*(((1+$B$11/12)^$A22-1)/($B$11/12))) | D22: =MAX(0,$B$7+$B$8*$A22)
A23: 6 | B23: =EDATE(TODAY(),$A23) | C23: =IF($B$11=0,$B$5+$B$13*$A23,$B$5*(1+$B$11/12)^$A23+$B$13*(((1+$B$11/12)^$A23-1)/($B$11/12))) | D23: =MAX(0,$B$7+$B$8*$A23)
A24: 7 | B24: =EDATE(TODAY(),$A24) | C24: =IF($B$11=0,$B$5+$B$13*$A24,$B$5*(1+$B$11/12)^$A24+$B$13*(((1+$B$11/12)^$A24-1)/($B$11/12))) | D24: =MAX(0,$B$7+$B$8*$A24)
A25: 8 | B25: =EDATE(TODAY(),$A25) | C25: =IF($B$11=0,$B$5+$B$13*$A25,$B$5*(1+$B$11/12)^$A25+$B$13*(((1+$B$11/12)^$A25-1)/($B$11/12))) | D25: =MAX(0,$B$7+$B$8*$A25)
A26: 9 | B26: =EDATE(TODAY(),$A26) | C26: =IF($B$11=0,$B$5+$B$13*$A26,$B$5*(1+$B$11/12)^$A26+$B$13*(((1+$B$11/12)^$A26-1)/($B$11/12))) | D26: =MAX(0,$B$7+$B$8*$A26)
A27: 10 | B27: =EDATE(TODAY(),$A27) | C27: =IF($B$11=0,$B$5+$B$13*$A27,$B$5*(1+$B$11/12)^$A27+$B$13*(((1+$B$11/12)^$A27-1)/($B$11/12))) | D27: =MAX(0,$B$7+$B$8*$A27)
A28: 11 | B28: =EDATE(TODAY(),$A28) | C28: =IF($B$11=0,$B$5+$B$13*$A28,$B$5*(1+$B$11/12)^$A28+$B$13*(((1+$B$11/12)^$A28-1)/($B$11/12))) | D28: =MAX(0,$B$7+$B$8*$A28)
A29: 12 | B29: =EDATE(TODAY(),$A29) | C29: =IF($B$11=0,$B$5+$B$13*$A29,$B$5*(1+$B$11/12)^$A29+$B$13*(((1+$B$11/12)^$A29-1)/($B$11/12))) | D29: =MAX(0,$B$7+$B$8*$A29)
A32: Formel Vermögen: Startwert verzinst plus monatliche Sparrate als nachschüssige Rente. Bei 0 % Rendite wird linear gerechnet. Der Ausgaben-Trend ist eine einfache lineare Regression über alle 24 Monatszeilen – solange leere Monate mit 0 € drinstehen, zieht er nach unten.

Sheet Einstellungen
A1: Einstellungen
A2: Kategorien, Monatsbudgets, Konten und Zahlungsrhythmen
A3: Kategorie | B3: Typ | C3: Monatsbudget (€) | D3: Notiz | F3: Konten / Zahlungsarten | H3: Zahlungsrhythmus
A4: Gehalt Werkstudent | B4: Einnahme | C4: 0 | F4: Girokonto | H4: monatlich
A5: Stipendium | B5: Einnahme | C5: 0 | F5: Tagesgeld / Sparkonto | H5: vierteljährlich
A6: Sonstige Einnahmen | B6: Einnahme | C6: 0 | F6: Kreditkarte | H6: halbjährlich
A7: Miete & Nebenkosten | B7: Ausgabe | C7: 0 | F7: Bargeld | H7: jährlich
A8: Strom & Internet | B8: Ausgabe | C8: 0 | F8: Depot
A9: Versicherungen | B9: Ausgabe | C9: 0 | F9: PayPal
A10: Lebensmittel | B10: Ausgabe | C10: 0
A11: Restaurant & Lieferdienst | B11: Ausgabe | C11: 0
A12: Mobilität & Auto | B12: Ausgabe | C12: 0
A13: Gesundheit & Drogerie | B13: Ausgabe | C13: 0
A14: Sport & Freizeit | B14: Ausgabe | C14: 0
A15: Kleidung | B15: Ausgabe | C15: 0
A16: Abos & Software | B16: Ausgabe | C16: 0
A17: Studium & Bücher | B17: Ausgabe | C17: 0
A18: Urlaub & Reisen | B18: Ausgabe | C18: 0
A19: Geschenke | B19: Ausgabe | C19: 0
A20: Sonstiges | B20: Ausgabe | C20: 0
A42: Summe Monatsbudget (nur Ausgaben) | C42: =SUMIF($B$4:$B$40,"Ausgabe",$C$4:$C$40)
A44: Typ muss exakt "Einnahme" oder "Ausgabe" heißen – davon hängen alle Auswertungen ab.
